switchbot_api/__init__.py
switchbot_api/alarm_info.py
switchbot_api/bot_information.py
switchbot_api/bot_types.py
switchbot_api/switchbot.py
switchbot_api/switchbot_scanner.py
python_switchbot_ble-0.1.0.dist-info/METADATA
python_switchbot_ble-0.1.0.dist-info/WHEEL
python_switchbot_ble-0.1.0.dist-info/licenses/LICENSE.txt
python_switchbot_ble-0.1.0.dist-info/RECORD
